motorized/__init__.py
motorized/beta.py
motorized/client.py
motorized/document.py
motorized/exceptions.py
motorized/keywords.py
motorized/migration.py
motorized/query.py
motorized/queryset.py
motorized/utils.py
motorized-0.7.1.dist-info/LICENSE.txt
motorized-0.7.1.dist-info/METADATA
motorized-0.7.1.dist-info/WHEEL
motorized-0.7.1.dist-info/RECORD
