Metadata-Version: 2.1
Name: motorized
Version: 0.7.1
Summary: Asyncio mongodb ODM based on pydantic
License: MIT
Keywords: MongoDB,Pydantic,Asyncio,ODM
Author: Sebastien Nicolet
Author-email: snicolet95@gmail.com
Requires-Python: >=3.11,<4.0
Classifier: License :: OSI Approved :: MIT License
Classifier: Programming Language :: Python :: 3
Classifier: Programming Language :: Python :: 3.11
Requires-Dist: depsolve (>=0.2.0,<0.3.0)
Requires-Dist: motor (>=3.1.1,<4.0.0)
Requires-Dist: pydantic (>=2.4.2,<3.0.0)
Requires-Dist: pydantic-partial (>=0.5.2,<0.6.0)
Project-URL: Documentation, https://github.com/Chr0nos/motorized/blob/master/README.md
